{"nodes": [{"id": "legal_privacy_policy", "label": "DreamLog Privacy Policy", "file_type": "document", "source_file": "docs/legal/PRIVACY_POLICY.md", "source_location": null, "source_url": null, "captured_at": null, "author": null, "contributor": null}, {"id": "legal_privacy_policy_audio_deletion", "label": "Audio Deletion Policy", "file_type": "concept", "source_file": "docs/legal/PRIVACY_POLICY.md", "source_location": null, "source_url": null, "captured_at": null, "author": null, "contributor": null}], "edges": [{"source": "legal_privacy_policy", "target": "legal_privacy_policy_audio_deletion", "relation": "references", "confidence": "EXTRACTED", "confidence_score": 1.0, "source_file": "docs/legal/PRIVACY_POLICY.md", "source_location": null, "weight": 1.0}, {"source": "legal_privacy_policy_audio_deletion", "target": "docs_decisions_adr_005", "relation": "semantically_similar_to", "confidence": "INFERRED", "confidence_score": 0.95, "source_file": "docs/legal/PRIVACY_POLICY.md", "source_location": null, "weight": 1.0}], "hyperedges": []}